[
  {
    "title": "20260314 0005",
    "file": "20260314_0005.jpg",
    "cover": "20260314_0005.jpg"
  },
  {
    "title": "20260314 0008",
    "file": "20260314_0008.jpg",
    "cover": "20260314_0008.jpg"
  },
  {
    "title": "20260314 0026",
    "file": "20260314_0026.jpg",
    "cover": "20260314_0026.jpg"
  },
  {
    "title": "20260314 0033",
    "file": "20260314_0033.jpg",
    "cover": "20260314_0033.jpg"
  },
  {
    "title": "20260318 0048",
    "file": "20260318_0048.jpg",
    "cover": "20260318_0048.jpg"
  },
  {
    "title": "20260318 0049",
    "file": "20260318_0049.jpg",
    "cover": "20260318_0049.jpg"
  },
  {
    "title": "20260318 0050",
    "file": "20260318_0050.jpg",
    "cover": "20260318_0050.jpg"
  },
  {
    "title": "20260426 0006",
    "file": "20260426_0006.jpg",
    "cover": "20260426_0006.jpg"
  },
  {
    "title": "20260426 0007",
    "file": "20260426_0007.jpg",
    "cover": "20260426_0007.jpg"
  },
  {
    "title": "20260426 0012",
    "file": "20260426_0012.jpg",
    "cover": "20260426_0012.jpg"
  },
  {
    "title": "20260426 0019",
    "file": "20260426_0019.jpg",
    "cover": "20260426_0019.jpg"
  },
  {
    "title": "20260426 0022",
    "file": "20260426_0022.jpg",
    "cover": "20260426_0022.jpg"
  },
  {
    "title": "IMG 20260329 185057",
    "file": "IMG_20260329_185057.png",
    "cover": "IMG_20260329_185057.png"
  },
  {
    "title": "IMG 20260502 125848 EDIT",
    "file": "IMG_20260502_125848_EDIT.png",
    "cover": "IMG_20260502_125848_EDIT.png"
  },
  {
    "title": "IMG 20260502 135928",
    "file": "IMG_20260502_135928.jpg",
    "cover": "IMG_20260502_135928.jpg"
  },
  {
    "title": "IMG 20260502 135936",
    "file": "IMG_20260502_135936.jpg",
    "cover": "IMG_20260502_135936.jpg"
  }
]